shipyard_athena/__init__.py
shipyard_athena/athena.py
shipyard_athena/cli/authtest.py
shipyard_athena/cli/download_query.py
shipyard_athena/cli/execute_query.py
shipyard_athena/errors/exceptions.py
shipyard_athena-0.2.0.dist-info/METADATA
shipyard_athena-0.2.0.dist-info/WHEEL
shipyard_athena-0.2.0.dist-info/RECORD
