Metadata-Version: 2.1
Name: shipyard-athena
Version: 0.2.0
Summary: A local client for connecting to and working with Amazon Athena
License: Apache 2.0
Author: wrp801
Author-email: wespoulsen@gmail.com
Requires-Python: >=3.9,<4.0
Classifier: License :: Other/Proprietary License
Classifier: Programming Language :: Python :: 3
Classifier: Programming Language :: Python :: 3.9
Classifier: Programming Language :: Python :: 3.10
Classifier: Programming Language :: Python :: 3.11
Requires-Dist: boto3 (>=1.34.59,<2.0.0)
Requires-Dist: shipyard-bp-utils (>=1.0.3,<2.0.0)
Requires-Dist: shipyard-templates (==0.6.2)
